<?xml version="1.0" encoding="UTF-8"?>
<objects serializationModel="Studio.02.02.00">
	<object class="AudioFile" id="{bfdf821d-2203-4b86-8759-1429a1fa4c21}">
		<property name="assetPath">
			<value>Social Bubble_Heartbeat.wav</value>
		</property>
		<property name="isStreaming">
			<value>true</value>
		</property>
		<property name="frequencyInKHz">
			<value>44.0999985</value>
		</property>
		<property name="channelCount">
			<value>2</value>
		</property>
		<property name="length">
			<value>140</value>
		</property>
		<relationship name="masterAssetFolder">
			<destination>{ab1e9e80-7df8-45e9-b817-387b9a9731bf}</destination>
		</relationship>
	</object>
</objects>
